flask_objectrocket.py
Flask_ObjectRocket-0.2.1.dist-info/DESCRIPTION.rst
Flask_ObjectRocket-0.2.1.dist-info/METADATA
Flask_ObjectRocket-0.2.1.dist-info/RECORD
Flask_ObjectRocket-0.2.1.dist-info/WHEEL
Flask_ObjectRocket-0.2.1.dist-info/metadata.json
Flask_ObjectRocket-0.2.1.dist-info/top_level.txt
