Metadata-Version: 2.0
Name: Flask-ObjectRocket
Version: 0.2.1
Summary: User authentication with the ObjectRocket API.
Home-page: https://github.com/objectrocket/flask-objectrocket
Author: Anthony Josiah Dodd
Author-email: dodd.anthonyjosiah@gmail.com
License: MIT
Platform: any
Classifier: Development Status :: 5 - Production/Stable
Classifier: Environment :: Web Environment
Classifier: Intended Audience :: Developers
Classifier: License :: OSI Approved :: MIT License
Classifier: Natural Language :: English
Classifier: Operating System :: OS Independent
Classifier: Programming Language :: Python
Classifier: Topic :: Internet :: WWW/HTTP :: Dynamic Content
Classifier: Topic :: Software Development :: Libraries :: Python Modules
Requires-Dist: Flask-RESTful (>=0.3,<1.0)
Requires-Dist: objectrocket (>=0.4,<1.0)
